jupyter_nbformat_client/__init__.py
jupyter_nbformat_client/__version__.py
jupyter_nbformat_client/_version.py
jupyter_nbformat_client-0.0.1.dist-info/METADATA
jupyter_nbformat_client-0.0.1.dist-info/WHEEL
jupyter_nbformat_client-0.0.1.dist-info/licenses/LICENSE
jupyter_nbformat_client-0.0.1.dist-info/RECORD
